{
  "main": {
    "id": "57e5e82ea817f34d",
    "type": "split",
    "children": [
      {
        "id": "2a0e7ea4843d3a64",
        "type": "tabs",
        "children": [
          {
            "id": "0355745ef69fb322",
            "type": "leaf",
            "state": {
              "type": "excalidraw",
              "state": {
                "file": "Research/Exploring the use of Personlised AI.excalidraw.md"
              }
            }
          },
          {
            "id": "f58aa24a18b51ebd",
            "type": "leaf",
            "state": {
              "type": "markdown",
              "state": {
                "file": "Computer Networks/Lecture Notes till Mid semester.md",
                "mode": "source",
                "backlinks": false,
                "source": false
              }
            }
          }
        ],
        "currentTab": 1
      }
    ],
    "direction": "vertical"
  },
  "left": {
    "id": "08732e7f56f4479f",
    "type": "split",
    "children": [
      {
        "id": "cc5d69f713d59cff",
        "type": "tabs",
        "children": [
          {
            "id": "fecbd33883a42f33",
            "type": "leaf",
            "state": {
              "type": "file-explorer",
              "state": {
                "sortOrder": "alphabetical"
              }
            }
          },
          {
            "id": "8d168cf15d11b6a0",
            "type": "leaf",
            "state": {
              "type": "search",
              "state": {
                "query": "tag:#packetswitching",
                "matchingCase": false,
                "explainSearch": false,
                "collapseAll": false,
                "extraContext": false,
                "sortOrder": "alphabetical"
              }
            }
          },
          {
            "id": "75c48d32a936cf8b",
            "type": "leaf",
            "state": {
              "type": "bookmarks",
              "state": {}
            }
          }
        ]
      }
    ],
    "direction": "horizontal",
    "width": 300,
    "collapsed": true
  },
  "right": {
    "id": "d690522f139902b6",
    "type": "split",
    "children": [
      {
        "id": "a48bd43f178aa285",
        "type": "tabs",
        "children": [
          {
            "id": "5c0fd7785eefe906",
            "type": "leaf",
            "state": {
              "type": "backlink",
              "state": {
                "file": "Computer Networks/Lecture Notes till Mid semester.md",
                "collapseAll": false,
                "extraContext": false,
                "sortOrder": "alphabetical",
                "showSearch": false,
                "searchQuery": "",
                "backlinkCollapsed": false,
                "unlinkedCollapsed": true
              }
            }
          },
          {
            "id": "fe64e9f7bfbb90b5",
            "type": "leaf",
            "state": {
              "type": "outgoing-link",
              "state": {
                "file": "Computer Networks/Lecture Notes till Mid semester.md",
                "linksCollapsed": false,
                "unlinkedCollapsed": true
              }
            }
          },
          {
            "id": "0318d6093d07754e",
            "type": "leaf",
            "state": {
              "type": "tag",
              "state": {
                "sortOrder": "frequency",
                "useHierarchy": true
              }
            }
          },
          {
            "id": "00301c202311bc4e",
            "type": "leaf",
            "state": {
              "type": "all-properties",
              "state": {
                "sortOrder": "frequency"
              }
            }
          },
          {
            "id": "adae13e52453fa78",
            "type": "leaf",
            "state": {
              "type": "outline",
              "state": {
                "file": "Computer Networks/Lecture Notes till Mid semester.md"
              }
            }
          }
        ],
        "currentTab": 2
      }
    ],
    "direction": "horizontal",
    "width": 300,
    "collapsed": true
  },
  "left-ribbon": {
    "hiddenItems": {
      "table-editor-obsidian:Advanced Tables Toolbar": false,
      "obsidian-excalidraw-plugin:Create new drawing": false,
      "switcher:Open quick switcher": false,
      "graph:Open graph view": false,
      "canvas:Create new canvas": false,
      "daily-notes:Open today's daily note": false,
      "templates:Insert template": false,
      "command-palette:Open command palette": false
    }
  },
  "active": "f58aa24a18b51ebd",
  "lastOpenFiles": [
    "CN book.excalidraw.md",
    "Computer Networks/Lecture Notes till Mid semester.md",
    "Computer Networking _ A Top Down Approach, 7th, converted.pdf",
    "Research/Exploring the use of Personlised AI.excalidraw.md",
    "Independent Project.md",
    "Age-Based Certification of Live-Stream Chats Using Sentiment Analysis.md",
    "Bishop-Pattern-Recognition-and-Machine-Learning-2006.pdf",
    "Exploring the Use of Personalised AI for Identifying Misinformation on Social Media.md",
    "Course.md",
    "Exploring_the_Use_of_Personalized_AI_for_Identifying_Misinformation_on_Social_Media.pdf",
    "Machine - Learning - Tom Mitchell.pdf",
    "Screenshot 2023-08-18 at 4.46.25 PM.png",
    "Screenshot 2023-08-18 at 4.46.25 PM 1.png",
    "Computer Networks/Assignments/CSE 232 Assignment 1.md",
    "Academic/Course/Machine Learning.md",
    "Screenshot 2023-08-18 at 4.46.34 PM 1.png.md",
    "Screenshot 2023-08-18 at 4.46.34 PM 1.png",
    "Screenshot 2023-08-18 at 4.46.34 PM.png",
    "Academic/Course/Computer Networks.md",
    "Computer Networks/Assignments",
    "Computer Networks",
    "Computer Networks/Lectures.md",
    "Computer Networks/lecture1.md",
    "Academic/Course/Lecture 1.md",
    "Research",
    "Academic/College DashBoard.md",
    "Academic/Courses",
    "Academic/Course/Software Development using Open Source.md",
    "Academic/Course",
    "github.com/shubham-attri.md",
    "hello/shubha.md",
    "hello",
    "Untitled.canvas",
    "Excalidraw/Drawing 2023-07-31 04.19.32.excalidraw.md",
    "2023-07-31.md"
  ]
}